ut_flt/__init__.py
ut_flt/__version__.py
ut_flt/flt.py
ut_flt/py.typed
ut_flt-2.0.0.20251020.dist-info/licenses/LICENSE.txt
ut_flt-2.0.0.20251020.dist-info/METADATA
ut_flt-2.0.0.20251020.dist-info/WHEEL
ut_flt-2.0.0.20251020.dist-info/top_level.txt
ut_flt-2.0.0.20251020.dist-info/RECORD
